MANIFEST.in
README.md
pyproject.toml
netbox_authorized_keys/__init__.py
netbox_authorized_keys/navigation.py
netbox_authorized_keys/search.py
netbox_authorized_keys/template_content.py
netbox_authorized_keys/urls.py
netbox_authorized_keys/version.py
netbox_authorized_keys.egg-info/PKG-INFO
netbox_authorized_keys.egg-info/SOURCES.txt
netbox_authorized_keys.egg-info/dependency_links.txt
netbox_authorized_keys.egg-info/top_level.txt
netbox_authorized_keys/api/__init__.py
netbox_authorized_keys/api/serializers.py
netbox_authorized_keys/api/serializers_credential.py
netbox_authorized_keys/api/urls.py
netbox_authorized_keys/api/views.py
netbox_authorized_keys/filtersets/__init__.py
netbox_authorized_keys/filtersets/authorizedkey.py
netbox_authorized_keys/filtersets/credential.py
netbox_authorized_keys/forms/__init__.py
netbox_authorized_keys/forms/authorizedkey.py
netbox_authorized_keys/forms/bulk_operation.py
netbox_authorized_keys/forms/credential.py
netbox_authorized_keys/forms/m2m_relation.py
netbox_authorized_keys/migrations/0001_initial.py
netbox_authorized_keys/migrations/0002_authorizedkey_full_name_and_more.py
netbox_authorized_keys/migrations/0003_alter_authorizedkeyvirtualmachine_options.py
netbox_authorized_keys/migrations/0004_alter_authorizedkeydevice_options.py
netbox_authorized_keys/migrations/0005_alter_authorizedkey_options.py
netbox_authorized_keys/migrations/0006_credential_credentialdevice_credential_devices_and_more.py
netbox_authorized_keys/migrations/0007_rename_key_fingerprint_credential_credential_storage_and_more.py
netbox_authorized_keys/migrations/__init__.py
netbox_authorized_keys/models/__init__.py
netbox_authorized_keys/models/authorizedkey.py
netbox_authorized_keys/models/credential.py
netbox_authorized_keys/tables/__init__.py
netbox_authorized_keys/tables/authorizedkey.py
netbox_authorized_keys/tables/credential.py
netbox_authorized_keys/templates/netbox_authorized_keys/authorized_key_tabview_table.html
netbox_authorized_keys/templates/netbox_authorized_keys/authorizedkey.html
netbox_authorized_keys/templates/netbox_authorized_keys/bulk_authorized_keys.html
