Metadata-Version: 2.4
Name: netbox-authorized-keys
Version: 3.0.0
Summary: NetBox plugin to store Authorized Keys
Author-email: Jan Krupa <jan.krupa@cesnet.cz>
License: MIT
Project-URL: Homepage, https://github.com/CESNET/netbox_authorized_keys
Project-URL: Repository, https://github.com/CESNET/netbox_authorized_keys
Project-URL: Bug Tracker, https://github.com/CESNET/netbox_authorized_keys/issues
Classifier: Development Status :: 4 - Beta
Classifier: Intended Audience :: Developers
Classifier: Intended Audience :: System Administrators
Classifier: Natural Language :: English
Classifier: Framework :: Django
Classifier: Programming Language :: Python :: 3 :: Only
Classifier: Programming Language :: Python :: 3.12
Classifier: Programming Language :: Python :: 3.13
Classifier: Programming Language :: Python :: 3.14
Requires-Python: >=3.12.0
